{
	"inputs" : 
	[
		{
			"path" : "CMakeLists.txt"
		},
		{
			"isGenerated" : true,
			"path" : "build/CMakeFiles/3.16.3/CMakeSystem.cmake"
		},
		{
			"isCMake" : true,
			"isExternal" : true,
			"path" : "/usr/share/cmake-3.16/Modules/CMakeSystemSpecificInitialize.cmake"
		},
		{
			"isGenerated" : true,
			"path" : "build/CMakeFiles/3.16.3/CMakeCCompiler.cmake"
		},
		{
			"isGenerated" : true,
			"path" : "build/CMakeFiles/3.16.3/CMakeCXXCompiler.cmake"
		},
		{
			"isCMake" : true,
			"isExternal" : true,
			"path" : "/usr/share/cmake-3.16/Modules/CMakeSystemSpecificInformation.cmake"
		},
		{
			"isCMake" : true,
			"isExternal" : true,
			"path" : "/usr/share/cmake-3.16/Modules/CMakeGenericSystem.cmake"
		},
		{
			"isCMake" : true,
			"isExternal" : true,
			"path" : "/usr/share/cmake-3.16/Modules/CMakeInitializeConfigs.cmake"
		},
		{
			"isCMake" : true,
			"isExternal" : true,
			"path" : "/usr/share/cmake-3.16/Modules/Platform/Linux.cmake"
		},
		{
			"isCMake" : true,
			"isExternal" : true,
			"path" : "/usr/share/cmake-3.16/Modules/Platform/UnixPaths.cmake"
		},
		{
			"isCMake" : true,
			"isExternal" : true,
			"path" : "/usr/share/cmake-3.16/Modules/CMakeCInformation.cmake"
		},
		{
			"isCMake" : true,
			"isExternal" : true,
			"path" : "/usr/share/cmake-3.16/Modules/CMakeLanguageInformation.cmake"
		},
		{
			"isCMake" : true,
			"isExternal" : true,
			"path" : "/usr/share/cmake-3.16/Modules/Compiler/GNU-C.cmake"
		},
		{
			"isCMake" : true,
			"isExternal" : true,
			"path" : "/usr/share/cmake-3.16/Modules/Compiler/GNU.cmake"
		},
		{
			"isCMake" : true,
			"isExternal" : true,
			"path" : "/usr/share/cmake-3.16/Modules/Compiler/CMakeCommonCompilerMacros.cmake"
		},
		{
			"isCMake" : true,
			"isExternal" : true,
			"path" : "/usr/share/cmake-3.16/Modules/Internal/CMakeCheckCompilerFlag.cmake"
		},
		{
			"isCMake" : true,
			"isExternal" : true,
			"path" : "/usr/share/cmake-3.16/Modules/CMakeCheckCompilerFlagCommonPatterns.cmake"
		},
		{
			"isCMake" : true,
			"isExternal" : true,
			"path" : "/usr/share/cmake-3.16/Modules/Platform/Linux-GNU-C.cmake"
		},
		{
			"isCMake" : true,
			"isExternal" : true,
			"path" : "/usr/share/cmake-3.16/Modules/Platform/Linux-GNU.cmake"
		},
		{
			"isCMake" : true,
			"isExternal" : true,
			"path" : "/usr/share/cmake-3.16/Modules/CMakeCommonLanguageInclude.cmake"
		},
		{
			"isCMake" : true,
			"isExternal" : true,
			"path" : "/usr/share/cmake-3.16/Modules/CMakeCXXInformation.cmake"
		},
		{
			"isCMake" : true,
			"isExternal" : true,
			"path" : "/usr/share/cmake-3.16/Modules/CMakeLanguageInformation.cmake"
		},
		{
			"isCMake" : true,
			"isExternal" : true,
			"path" : "/usr/share/cmake-3.16/Modules/Compiler/GNU-CXX.cmake"
		},
		{
			"isCMake" : true,
			"isExternal" : true,
			"path" : "/usr/share/cmake-3.16/Modules/Compiler/GNU.cmake"
		},
		{
			"isCMake" : true,
			"isExternal" : true,
			"path" : "/usr/share/cmake-3.16/Modules/Platform/Linux-GNU-CXX.cmake"
		},
		{
			"isCMake" : true,
			"isExternal" : true,
			"path" : "/usr/share/cmake-3.16/Modules/Platform/Linux-GNU.cmake"
		},
		{
			"isCMake" : true,
			"isExternal" : true,
			"path" : "/usr/share/cmake-3.16/Modules/CMakeCommonLanguageInclude.cmake"
		},
		{
			"path" : "cmake/modules/SRSRANVersion.cmake"
		},
		{
			"path" : "cmake/modules/SRSRANPackage.cmake"
		},
		{
			"isCMake" : true,
			"isExternal" : true,
			"path" : "/usr/share/cmake-3.16/Modules/CPack.cmake"
		},
		{
			"isCMake" : true,
			"isExternal" : true,
			"path" : "/usr/share/cmake-3.16/Modules/CPackComponent.cmake"
		},
		{
			"isExternal" : true,
			"path" : "/usr/share/cmake-3.16/Templates/CPackConfig.cmake.in"
		},
		{
			"isExternal" : true,
			"path" : "/usr/share/cmake-3.16/Templates/CPackConfig.cmake.in"
		},
		{
			"isCMake" : true,
			"isExternal" : true,
			"path" : "/usr/share/cmake-3.16/Modules/CTest.cmake"
		},
		{
			"isCMake" : true,
			"isExternal" : true,
			"path" : "/usr/share/cmake-3.16/Modules/CTestUseLaunchers.cmake"
		},
		{
			"path" : "CTestConfig.cmake"
		},
		{
			"isCMake" : true,
			"isExternal" : true,
			"path" : "/usr/share/cmake-3.16/Modules/CTestTargets.cmake"
		},
		{
			"isCMake" : true,
			"isExternal" : true,
			"path" : "/usr/share/cmake-3.16/Modules/DartConfiguration.tcl.in"
		},
		{
			"path" : "CTestCustom.cmake.in"
		},
		{
			"path" : "cmake/modules/SRSRANbuildinfo.cmake.in"
		},
		{
			"path" : "cmake/modules/CheckAtomic.cmake"
		},
		{
			"isCMake" : true,
			"isExternal" : true,
			"path" : "/usr/share/cmake-3.16/Modules/CheckCXXSourceCompiles.cmake"
		},
		{
			"isCMake" : true,
			"isExternal" : true,
			"path" : "/usr/share/cmake-3.16/Modules/CheckLibraryExists.cmake"
		},
		{
			"isCMake" : true,
			"isExternal" : true,
			"path" : "/usr/share/cmake-3.16/Modules/FindThreads.cmake"
		},
		{
			"isCMake" : true,
			"isExternal" : true,
			"path" : "/usr/share/cmake-3.16/Modules/CheckLibraryExists.cmake"
		},
		{
			"isCMake" : true,
			"isExternal" : true,
			"path" : "/usr/share/cmake-3.16/Modules/CheckIncludeFile.cmake"
		},
		{
			"isCMake" : true,
			"isExternal" : true,
			"path" : "/usr/share/cmake-3.16/Modules/CheckCSourceCompiles.cmake"
		},
		{
			"isCMake" : true,
			"isExternal" : true,
			"path" : "/usr/share/cmake-3.16/Modules/FindPackageHandleStandardArgs.cmake"
		},
		{
			"isCMake" : true,
			"isExternal" : true,
			"path" : "/usr/share/cmake-3.16/Modules/FindPackageMessage.cmake"
		},
		{
			"path" : "cmake/modules/FindFFTW3F.cmake"
		},
		{
			"isCMake" : true,
			"isExternal" : true,
			"path" : "/usr/share/cmake-3.16/Modules/FindPkgConfig.cmake"
		},
		{
			"isCMake" : true,
			"isExternal" : true,
			"path" : "/usr/share/cmake-3.16/Modules/FindPackageHandleStandardArgs.cmake"
		},
		{
			"isCMake" : true,
			"isExternal" : true,
			"path" : "/usr/share/cmake-3.16/Modules/FindPackageMessage.cmake"
		},
		{
			"isCMake" : true,
			"isExternal" : true,
			"path" : "/usr/share/cmake-3.16/Modules/FindPackageHandleStandardArgs.cmake"
		},
		{
			"isCMake" : true,
			"isExternal" : true,
			"path" : "/usr/share/cmake-3.16/Modules/FindPackageMessage.cmake"
		},
		{
			"path" : "cmake/modules/FindMbedTLS.cmake"
		},
		{
			"isCMake" : true,
			"isExternal" : true,
			"path" : "/usr/share/cmake-3.16/Modules/FindPkgConfig.cmake"
		},
		{
			"isCMake" : true,
			"isExternal" : true,
			"path" : "/usr/share/cmake-3.16/Modules/FindPackageHandleStandardArgs.cmake"
		},
		{
			"isCMake" : true,
			"isExternal" : true,
			"path" : "/usr/share/cmake-3.16/Modules/FindPackageMessage.cmake"
		},
		{
			"isCMake" : true,
			"isExternal" : true,
			"path" : "/usr/share/cmake-3.16/Modules/FindPackageHandleStandardArgs.cmake"
		},
		{
			"isCMake" : true,
			"isExternal" : true,
			"path" : "/usr/share/cmake-3.16/Modules/FindPackageMessage.cmake"
		},
		{
			"path" : "cmake/modules/FindPCSCLite.cmake"
		},
		{
			"isCMake" : true,
			"isExternal" : true,
			"path" : "/usr/share/cmake-3.16/Modules/FindPkgConfig.cmake"
		},
		{
			"isCMake" : true,
			"isExternal" : true,
			"path" : "/usr/share/cmake-3.16/Modules/FindPackageHandleStandardArgs.cmake"
		},
		{
			"isCMake" : true,
			"isExternal" : true,
			"path" : "/usr/share/cmake-3.16/Modules/FindPackageMessage.cmake"
		},
		{
			"isCMake" : true,
			"isExternal" : true,
			"path" : "/usr/share/cmake-3.16/Modules/FindPackageHandleStandardArgs.cmake"
		},
		{
			"isCMake" : true,
			"isExternal" : true,
			"path" : "/usr/share/cmake-3.16/Modules/FindPackageMessage.cmake"
		},
		{
			"path" : "cmake/modules/FindUHD.cmake"
		},
		{
			"isCMake" : true,
			"isExternal" : true,
			"path" : "/usr/share/cmake-3.16/Modules/FindPkgConfig.cmake"
		},
		{
			"isCMake" : true,
			"isExternal" : true,
			"path" : "/usr/share/cmake-3.16/Modules/FindPackageHandleStandardArgs.cmake"
		},
		{
			"isCMake" : true,
			"isExternal" : true,
			"path" : "/usr/share/cmake-3.16/Modules/FindPackageMessage.cmake"
		},
		{
			"isCMake" : true,
			"isExternal" : true,
			"path" : "/usr/share/cmake-3.16/Modules/FindPackageHandleStandardArgs.cmake"
		},
		{
			"isCMake" : true,
			"isExternal" : true,
			"path" : "/usr/share/cmake-3.16/Modules/FindPackageMessage.cmake"
		},
		{
			"isCMake" : true,
			"isExternal" : true,
			"path" : "/usr/share/cmake-3.16/Modules/CheckCXXSourceCompiles.cmake"
		},
		{
			"path" : "cmake/modules/FindSKIQ.cmake"
		},
		{
			"isCMake" : true,
			"isExternal" : true,
			"path" : "/usr/share/cmake-3.16/Modules/FindPkgConfig.cmake"
		},
		{
			"isCMake" : true,
			"isExternal" : true,
			"path" : "/usr/share/cmake-3.16/Modules/FindPackageHandleStandardArgs.cmake"
		},
		{
			"isCMake" : true,
			"isExternal" : true,
			"path" : "/usr/share/cmake-3.16/Modules/FindPackageMessage.cmake"
		},
		{
			"isCMake" : true,
			"isExternal" : true,
			"path" : "/usr/share/cmake-3.16/Modules/FindPackageHandleStandardArgs.cmake"
		},
		{
			"isCMake" : true,
			"isExternal" : true,
			"path" : "/usr/share/cmake-3.16/Modules/FindPackageMessage.cmake"
		},
		{
			"path" : "cmake/modules/FindbladeRF.cmake"
		},
		{
			"path" : "cmake/modules/FindSoapySDR.cmake"
		},
		{
			"path" : "cmake/modules/FindZeroMQ.cmake"
		},
		{
			"isCMake" : true,
			"isExternal" : true,
			"path" : "/usr/share/cmake-3.16/Modules/FindBoost.cmake"
		},
		{
			"isCMake" : true,
			"isExternal" : true,
			"path" : "/usr/share/cmake-3.16/Modules/FindPackageHandleStandardArgs.cmake"
		},
		{
			"isCMake" : true,
			"isExternal" : true,
			"path" : "/usr/share/cmake-3.16/Modules/FindPackageMessage.cmake"
		},
		{
			"isExternal" : true,
			"path" : "/usr/lib/x86_64-linux-gnu/cmake/Boost-1.71.0/BoostConfigVersion.cmake"
		},
		{
			"isExternal" : true,
			"path" : "/usr/lib/x86_64-linux-gnu/cmake/Boost-1.71.0/BoostConfig.cmake"
		},
		{
			"isExternal" : true,
			"path" : "/usr/lib/x86_64-linux-gnu/cmake/boost_headers-1.71.0/boost_headers-config-version.cmake"
		},
		{
			"isExternal" : true,
			"path" : "/usr/lib/x86_64-linux-gnu/cmake/boost_headers-1.71.0/boost_headers-config.cmake"
		},
		{
			"isExternal" : true,
			"path" : "/usr/lib/x86_64-linux-gnu/cmake/boost_program_options-1.71.0/boost_program_options-config-version.cmake"
		},
		{
			"isExternal" : true,
			"path" : "/usr/lib/x86_64-linux-gnu/cmake/boost_program_options-1.71.0/boost_program_options-config.cmake"
		},
		{
			"isExternal" : true,
			"path" : "/usr/lib/x86_64-linux-gnu/cmake/BoostDetectToolset-1.71.0.cmake"
		},
		{
			"isExternal" : true,
			"path" : "/usr/lib/x86_64-linux-gnu/cmake/boost_program_options-1.71.0/libboost_program_options-variant-shared.cmake"
		},
		{
			"isExternal" : true,
			"path" : "/usr/lib/x86_64-linux-gnu/cmake/boost_program_options-1.71.0/libboost_program_options-variant-static.cmake"
		},
		{
			"isExternal" : true,
			"path" : "/usr/lib/x86_64-linux-gnu/cmake/boost_headers-1.71.0/boost_headers-config-version.cmake"
		},
		{
			"isExternal" : true,
			"path" : "/usr/lib/x86_64-linux-gnu/cmake/boost_headers-1.71.0/boost_headers-config.cmake"
		},
		{
			"path" : "cmake/modules/FindSRSGUI.cmake"
		},
		{
			"isCMake" : true,
			"isExternal" : true,
			"path" : "/usr/share/cmake-3.16/Modules/FindPkgConfig.cmake"
		},
		{
			"isCMake" : true,
			"isExternal" : true,
			"path" : "/usr/share/cmake-3.16/Modules/FindPackageHandleStandardArgs.cmake"
		},
		{
			"isCMake" : true,
			"isExternal" : true,
			"path" : "/usr/share/cmake-3.16/Modules/FindPackageMessage.cmake"
		},
		{
			"isCMake" : true,
			"isExternal" : true,
			"path" : "/usr/share/cmake-3.16/Modules/FindPackageHandleStandardArgs.cmake"
		},
		{
			"isCMake" : true,
			"isExternal" : true,
			"path" : "/usr/share/cmake-3.16/Modules/FindPackageMessage.cmake"
		},
		{
			"path" : "cmake/modules/FindBackward.cmake"
		},
		{
			"isCMake" : true,
			"isExternal" : true,
			"path" : "/usr/share/cmake-3.16/Modules/FindPackageHandleStandardArgs.cmake"
		},
		{
			"isCMake" : true,
			"isExternal" : true,
			"path" : "/usr/share/cmake-3.16/Modules/FindPackageMessage.cmake"
		},
		{
			"isCMake" : true,
			"isExternal" : true,
			"path" : "/usr/share/cmake-3.16/Modules/FindPackageHandleStandardArgs.cmake"
		},
		{
			"isCMake" : true,
			"isExternal" : true,
			"path" : "/usr/share/cmake-3.16/Modules/FindPackageMessage.cmake"
		},
		{
			"path" : "cmake/modules/SRSRAN_install_configs.sh.in"
		},
		{
			"isCMake" : true,
			"isExternal" : true,
			"path" : "/usr/share/cmake-3.16/Modules/CheckCXXCompilerFlag.cmake"
		},
		{
			"isCMake" : true,
			"isExternal" : true,
			"path" : "/usr/share/cmake-3.16/Modules/CheckCXXSourceCompiles.cmake"
		},
		{
			"isCMake" : true,
			"isExternal" : true,
			"path" : "/usr/share/cmake-3.16/Modules/CMakeCheckCompilerFlagCommonPatterns.cmake"
		},
		{
			"path" : "cmake/modules/FindSSE.cmake"
		},
		{
			"path" : "cmake/modules/CheckCSourceRuns.cmake"
		},
		{
			"isCMake" : true,
			"isExternal" : true,
			"path" : "/usr/share/cmake-3.16/Modules/CheckCCompilerFlag.cmake"
		},
		{
			"isCMake" : true,
			"isExternal" : true,
			"path" : "/usr/share/cmake-3.16/Modules/CheckCSourceCompiles.cmake"
		},
		{
			"isCMake" : true,
			"isExternal" : true,
			"path" : "/usr/share/cmake-3.16/Modules/CMakeCheckCompilerFlagCommonPatterns.cmake"
		},
		{
			"isCMake" : true,
			"isExternal" : true,
			"path" : "/usr/share/cmake-3.16/Modules/CheckCXXCompilerFlag.cmake"
		},
		{
			"isCMake" : true,
			"isExternal" : true,
			"path" : "/usr/share/cmake-3.16/Modules/CheckCCompilerFlag.cmake"
		},
		{
			"isCMake" : true,
			"isExternal" : true,
			"path" : "/usr/share/cmake-3.16/Modules/CheckCCompilerFlag.cmake"
		},
		{
			"path" : "cmake/modules/FindSSE.cmake"
		},
		{
			"path" : "cmake/modules/CheckCSourceRuns.cmake"
		},
		{
			"path" : "cmake_uninstall.cmake.in"
		},
		{
			"path" : "lib/CMakeLists.txt"
		},
		{
			"path" : "lib/src/CMakeLists.txt"
		},
		{
			"path" : "lib/src/asn1/CMakeLists.txt"
		},
		{
			"path" : "lib/src/common/CMakeLists.txt"
		},
		{
			"path" : "lib/src/common/test/CMakeLists.txt"
		},
		{
			"path" : "lib/src/mac/CMakeLists.txt"
		},
		{
			"path" : "lib/src/mac/test/CMakeLists.txt"
		},
		{
			"path" : "lib/src/phy/CMakeLists.txt"
		},
		{
			"path" : "lib/src/phy/agc/CMakeLists.txt"
		},
		{
			"path" : "lib/src/phy/ch_estimation/CMakeLists.txt"
		},
		{
			"path" : "lib/src/phy/ch_estimation/test/CMakeLists.txt"
		},
		{
			"path" : "lib/src/phy/common/CMakeLists.txt"
		},
		{
			"path" : "lib/src/phy/common/test/CMakeLists.txt"
		},
		{
			"path" : "lib/src/phy/fec/CMakeLists.txt"
		},
		{
			"path" : "lib/src/phy/fec/block/CMakeLists.txt"
		},
		{
			"path" : "lib/src/phy/fec/block/test/CMakeLists.txt"
		},
		{
			"path" : "lib/src/phy/fec/convolutional/CMakeLists.txt"
		},
		{
			"path" : "lib/src/phy/fec/convolutional/test/CMakeLists.txt"
		},
		{
			"path" : "lib/src/phy/fec/ldpc/CMakeLists.txt"
		},
		{
			"path" : "lib/src/phy/fec/ldpc/test/CMakeLists.txt"
		},
		{
			"path" : "lib/src/phy/fec/polar/CMakeLists.txt"
		},
		{
			"path" : "lib/src/phy/fec/polar/test/CMakeLists.txt"
		},
		{
			"path" : "lib/src/phy/fec/test/CMakeLists.txt"
		},
		{
			"path" : "lib/src/phy/fec/turbo/CMakeLists.txt"
		},
		{
			"path" : "lib/src/phy/fec/turbo/test/CMakeLists.txt"
		},
		{
			"path" : "lib/src/phy/mimo/CMakeLists.txt"
		},
		{
			"path" : "lib/src/phy/mimo/test/CMakeLists.txt"
		},
		{
			"path" : "lib/src/phy/phch/CMakeLists.txt"
		},
		{
			"path" : "lib/src/phy/phch/test/CMakeLists.txt"
		},
		{
			"path" : "lib/src/phy/rf/CMakeLists.txt"
		},
		{
			"path" : "lib/src/phy/sync/CMakeLists.txt"
		},
		{
			"path" : "lib/src/phy/sync/test/CMakeLists.txt"
		},
		{
			"path" : "lib/src/phy/utils/CMakeLists.txt"
		},
		{
			"path" : "lib/src/phy/utils/test/CMakeLists.txt"
		},
		{
			"path" : "lib/src/phy/channel/CMakeLists.txt"
		},
		{
			"path" : "lib/src/phy/channel/test/CMakeLists.txt"
		},
		{
			"path" : "lib/src/phy/dft/CMakeLists.txt"
		},
		{
			"path" : "lib/src/phy/dft/test/CMakeLists.txt"
		},
		{
			"path" : "lib/src/phy/io/CMakeLists.txt"
		},
		{
			"path" : "lib/src/phy/modem/CMakeLists.txt"
		},
		{
			"path" : "lib/src/phy/modem/test/CMakeLists.txt"
		},
		{
			"path" : "lib/src/phy/resampling/CMakeLists.txt"
		},
		{
			"path" : "lib/src/phy/resampling/test/CMakeLists.txt"
		},
		{
			"path" : "lib/src/phy/scrambling/CMakeLists.txt"
		},
		{
			"path" : "lib/src/phy/scrambling/test/CMakeLists.txt"
		},
		{
			"path" : "lib/src/phy/ue/CMakeLists.txt"
		},
		{
			"path" : "lib/src/phy/ue/test/CMakeLists.txt"
		},
		{
			"path" : "lib/src/phy/enb/CMakeLists.txt"
		},
		{
			"path" : "lib/src/phy/gnb/CMakeLists.txt"
		},
		{
			"path" : "lib/src/phy/cfr/CMakeLists.txt"
		},
		{
			"path" : "lib/src/phy/cfr/test/CMakeLists.txt"
		},
		{
			"path" : "lib/src/radio/CMakeLists.txt"
		},
		{
			"path" : "lib/src/radio/test/CMakeLists.txt"
		},
		{
			"path" : "lib/src/rlc/CMakeLists.txt"
		},
		{
			"path" : "lib/src/pdcp/CMakeLists.txt"
		},
		{
			"path" : "lib/src/gtpu/CMakeLists.txt"
		},
		{
			"path" : "lib/src/srslog/CMakeLists.txt"
		},
		{
			"isCMake" : true,
			"isExternal" : true,
			"path" : "/usr/share/cmake-3.16/Modules/FindThreads.cmake"
		},
		{
			"isCMake" : true,
			"isExternal" : true,
			"path" : "/usr/share/cmake-3.16/Modules/CheckLibraryExists.cmake"
		},
		{
			"isCMake" : true,
			"isExternal" : true,
			"path" : "/usr/share/cmake-3.16/Modules/CheckIncludeFile.cmake"
		},
		{
			"isCMake" : true,
			"isExternal" : true,
			"path" : "/usr/share/cmake-3.16/Modules/CheckCSourceCompiles.cmake"
		},
		{
			"isCMake" : true,
			"isExternal" : true,
			"path" : "/usr/share/cmake-3.16/Modules/FindPackageHandleStandardArgs.cmake"
		},
		{
			"isCMake" : true,
			"isExternal" : true,
			"path" : "/usr/share/cmake-3.16/Modules/FindPackageMessage.cmake"
		},
		{
			"path" : "lib/src/support/CMakeLists.txt"
		},
		{
			"path" : "lib/src/system/CMakeLists.txt"
		},
		{
			"isCMake" : true,
			"isExternal" : true,
			"path" : "/usr/share/cmake-3.16/Modules/FindThreads.cmake"
		},
		{
			"isCMake" : true,
			"isExternal" : true,
			"path" : "/usr/share/cmake-3.16/Modules/CheckLibraryExists.cmake"
		},
		{
			"isCMake" : true,
			"isExternal" : true,
			"path" : "/usr/share/cmake-3.16/Modules/CheckIncludeFile.cmake"
		},
		{
			"isCMake" : true,
			"isExternal" : true,
			"path" : "/usr/share/cmake-3.16/Modules/CheckCSourceCompiles.cmake"
		},
		{
			"isCMake" : true,
			"isExternal" : true,
			"path" : "/usr/share/cmake-3.16/Modules/FindPackageHandleStandardArgs.cmake"
		},
		{
			"isCMake" : true,
			"isExternal" : true,
			"path" : "/usr/share/cmake-3.16/Modules/FindPackageMessage.cmake"
		},
		{
			"path" : "lib/include/CMakeLists.txt"
		},
		{
			"path" : "lib/include/srsran/CMakeLists.txt"
		},
		{
			"path" : "lib/include/srsran/version.h.in"
		},
		{
			"path" : "lib/examples/CMakeLists.txt"
		},
		{
			"path" : "lib/examples/test/CMakeLists.txt"
		},
		{
			"path" : "lib/test/CMakeLists.txt"
		},
		{
			"path" : "lib/test/asn1/CMakeLists.txt"
		},
		{
			"path" : "lib/test/common/CMakeLists.txt"
		},
		{
			"path" : "cmake/modules/FindSCTP.cmake"
		},
		{
			"isCMake" : true,
			"isExternal" : true,
			"path" : "/usr/share/cmake-3.16/Modules/FindPkgConfig.cmake"
		},
		{
			"isCMake" : true,
			"isExternal" : true,
			"path" : "/usr/share/cmake-3.16/Modules/FindPackageHandleStandardArgs.cmake"
		},
		{
			"isCMake" : true,
			"isExternal" : true,
			"path" : "/usr/share/cmake-3.16/Modules/FindPackageMessage.cmake"
		},
		{
			"isCMake" : true,
			"isExternal" : true,
			"path" : "/usr/share/cmake-3.16/Modules/FindPackageHandleStandardArgs.cmake"
		},
		{
			"isCMake" : true,
			"isExternal" : true,
			"path" : "/usr/share/cmake-3.16/Modules/FindPackageMessage.cmake"
		},
		{
			"path" : "lib/test/phy/CMakeLists.txt"
		},
		{
			"path" : "lib/test/srslog/CMakeLists.txt"
		},
		{
			"path" : "lib/test/rlc/CMakeLists.txt"
		},
		{
			"path" : "lib/test/pdcp/CMakeLists.txt"
		},
		{
			"path" : "lib/test/adt/CMakeLists.txt"
		},
		{
			"path" : "srsue/CMakeLists.txt"
		},
		{
			"path" : "srsue/src/CMakeLists.txt"
		},
		{
			"path" : "srsue/src/phy/CMakeLists.txt"
		},
		{
			"path" : "srsue/src/phy/test/CMakeLists.txt"
		},
		{
			"path" : "srsue/src/stack/CMakeLists.txt"
		},
		{
			"path" : "srsue/src/stack/mac_common/CMakeLists.txt"
		},
		{
			"path" : "srsue/src/stack/mac/CMakeLists.txt"
		},
		{
			"path" : "srsue/src/stack/mac/test/CMakeLists.txt"
		},
		{
			"path" : "srsue/src/stack/mac_nr/CMakeLists.txt"
		},
		{
			"path" : "srsue/src/stack/mac_nr/test/CMakeLists.txt"
		},
		{
			"path" : "srsue/src/stack/rrc/CMakeLists.txt"
		},
		{
			"path" : "srsue/src/stack/rrc/test/CMakeLists.txt"
		},
		{
			"path" : "srsue/src/stack/rrc_nr/CMakeLists.txt"
		},
		{
			"path" : "srsue/src/stack/rrc_nr/test/CMakeLists.txt"
		},
		{
			"path" : "srsue/src/stack/upper/CMakeLists.txt"
		},
		{
			"path" : "srsue/src/stack/upper/test/CMakeLists.txt"
		},
		{
			"path" : "srsue/src/test/CMakeLists.txt"
		},
		{
			"path" : "srsenb/CMakeLists.txt"
		},
		{
			"path" : "cmake/modules/FindLibConfig.cmake"
		},
		{
			"path" : "cmake/modules/FindSCTP.cmake"
		},
		{
			"isCMake" : true,
			"isExternal" : true,
			"path" : "/usr/share/cmake-3.16/Modules/FindPkgConfig.cmake"
		},
		{
			"isCMake" : true,
			"isExternal" : true,
			"path" : "/usr/share/cmake-3.16/Modules/FindPackageHandleStandardArgs.cmake"
		},
		{
			"isCMake" : true,
			"isExternal" : true,
			"path" : "/usr/share/cmake-3.16/Modules/FindPackageMessage.cmake"
		},
		{
			"isCMake" : true,
			"isExternal" : true,
			"path" : "/usr/share/cmake-3.16/Modules/FindPackageHandleStandardArgs.cmake"
		},
		{
			"isCMake" : true,
			"isExternal" : true,
			"path" : "/usr/share/cmake-3.16/Modules/FindPackageMessage.cmake"
		},
		{
			"path" : "srsenb/src/CMakeLists.txt"
		},
		{
			"path" : "srsenb/src/common/CMakeLists.txt"
		},
		{
			"path" : "srsenb/src/phy/CMakeLists.txt"
		},
		{
			"path" : "srsenb/src/stack/CMakeLists.txt"
		},
		{
			"path" : "srsenb/src/stack/mac/CMakeLists.txt"
		},
		{
			"path" : "srsenb/src/stack/mac/common/CMakeLists.txt"
		},
		{
			"path" : "srsenb/src/stack/mac/schedulers/CMakeLists.txt"
		},
		{
			"path" : "srsenb/src/stack/rrc/CMakeLists.txt"
		},
		{
			"path" : "srsenb/src/stack/s1ap/CMakeLists.txt"
		},
		{
			"path" : "srsenb/src/stack/upper/CMakeLists.txt"
		},
		{
			"path" : "srsenb/test/CMakeLists.txt"
		},
		{
			"path" : "srsenb/test/mac/CMakeLists.txt"
		},
		{
			"path" : "srsenb/test/phy/CMakeLists.txt"
		},
		{
			"path" : "srsenb/test/upper/CMakeLists.txt"
		},
		{
			"path" : "srsenb/test/rrc/CMakeLists.txt"
		},
		{
			"path" : "srsenb/test/s1ap/CMakeLists.txt"
		},
		{
			"path" : "srsgnb/CMakeLists.txt"
		},
		{
			"path" : "srsgnb/src/CMakeLists.txt"
		},
		{
			"path" : "srsgnb/src/stack/CMakeLists.txt"
		},
		{
			"path" : "srsgnb/src/stack/mac/CMakeLists.txt"
		},
		{
			"path" : "srsgnb/src/stack/mac/test/CMakeLists.txt"
		},
		{
			"path" : "srsgnb/src/stack/ngap/CMakeLists.txt"
		},
		{
			"path" : "srsgnb/src/stack/ngap/test/CMakeLists.txt"
		},
		{
			"path" : "srsgnb/src/stack/rrc/CMakeLists.txt"
		},
		{
			"path" : "srsgnb/src/stack/rrc/test/CMakeLists.txt"
		},
		{
			"path" : "srsgnb/src/stack/sdap/CMakeLists.txt"
		},
		{
			"path" : "srsepc/CMakeLists.txt"
		},
		{
			"path" : "cmake/modules/FindLibConfig.cmake"
		},
		{
			"path" : "cmake/modules/FindSCTP.cmake"
		},
		{
			"isCMake" : true,
			"isExternal" : true,
			"path" : "/usr/share/cmake-3.16/Modules/FindPkgConfig.cmake"
		},
		{
			"isCMake" : true,
			"isExternal" : true,
			"path" : "/usr/share/cmake-3.16/Modules/FindPackageHandleStandardArgs.cmake"
		},
		{
			"isCMake" : true,
			"isExternal" : true,
			"path" : "/usr/share/cmake-3.16/Modules/FindPackageMessage.cmake"
		},
		{
			"isCMake" : true,
			"isExternal" : true,
			"path" : "/usr/share/cmake-3.16/Modules/FindPackageHandleStandardArgs.cmake"
		},
		{
			"isCMake" : true,
			"isExternal" : true,
			"path" : "/usr/share/cmake-3.16/Modules/FindPackageMessage.cmake"
		},
		{
			"path" : "srsepc/src/CMakeLists.txt"
		},
		{
			"path" : "srsepc/src/mme/CMakeLists.txt"
		},
		{
			"path" : "srsepc/src/hss/CMakeLists.txt"
		},
		{
			"path" : "srsepc/src/spgw/CMakeLists.txt"
		},
		{
			"path" : "srsepc/src/mbms-gw/CMakeLists.txt"
		},
		{
			"path" : "test/CMakeLists.txt"
		},
		{
			"path" : "test/phy/CMakeLists.txt"
		}
	],
	"kind" : "cmakeFiles",
	"paths" : 
	{
		"build" : "/home/user/srsran/build",
		"source" : "/home/user/srsran"
	},
	"version" : 
	{
		"major" : 1,
		"minor" : 0
	}
}
